detectionDataCollection/__init__.py
detectionDataCollection/detectionDataCollection.py
detection_datacollection-0.1.0.dist-info/licenses/LICENSE
detection_datacollection-0.1.0.dist-info/METADATA
detection_datacollection-0.1.0.dist-info/WHEEL
detection_datacollection-0.1.0.dist-info/top_level.txt
detection_datacollection-0.1.0.dist-info/RECORD
