Metadata-Version: 2.4
Name: detection-datacollection
Version: 0.1.0
Summary: A tool for collecting object detection datasets with OpenCV
Author: Shashwat dev Hans
Author-email: Shashwat dev hans <shashwatdevhans@gmail.com>
License: MIT License
Requires-Python: >=3.6
License-File: LICENSE
Requires-Dist: numpy==2.2.6
Requires-Dist: opencv-python==4.12.0.88
Requires-Dist: PyYAML==6.0.2
Dynamic: author
Dynamic: license-file
Dynamic: requires-python
